dnszone/__init__.py
dnszone/dnszone.py
dnszone/version.py
dnszone/zone_check.py
dnszone/zone_reload.py
dnszone-3.1.1.dist-info/LICENSE
dnszone-3.1.1.dist-info/METADATA
dnszone-3.1.1.dist-info/WHEEL
dnszone-3.1.1.dist-info/top_level.txt
dnszone-3.1.1.dist-info/RECORD
