Metadata-Version: 2.1
Name: dnszone
Version: 3.1.1
Summary: Fork of Easy Zone - DNS Zone abstraction module
Author-email: Greg Hellings <greg.hellings@gmail.com>
License: Copyright 2019 Greg Hellings (greg.hellings@gmail.com)
Project-URL: homepage, https://github.com/greg-hellings/dnszone
Project-URL: repository, https://github.com/greg-hellings/dnszone
Classifier: Programming Language :: Python :: 3
Classifier: Development Status :: 4 - Beta
Classifier: License :: OSI Approved :: MIT License
Classifier: Topic :: Internet :: Name Service (DNS)
Classifier: Topic :: System :: Systems Administration
Requires-Python: >=3.8
License-File: LICENSE
Requires-Dist: dnspython (<2)
Requires-Dist: six
